src/__init__.py
src/operation.py
tests/__init__.py
tests/test_operation.py
arithmeticops-0.1.dist-info/LICENSE
arithmeticops-0.1.dist-info/METADATA
arithmeticops-0.1.dist-info/WHEEL
arithmeticops-0.1.dist-info/top_level.txt
arithmeticops-0.1.dist-info/RECORD
