Metadata-Version: 2.1
Name: arithmeticops
Version: 0.1
Summary: A simple package for basic arithmetic operations using classes and objects
Home-page: https://bitbucket.vih.infineon.com/scm/~paridasubidk/arithmeticops.git
Author: Your Name
Author-email: subidkumar.parida-EE@infineon.com
License: MIT
Classifier: Programming Language :: Python :: 3
Classifier: License :: OSI Approved :: MIT License
Classifier: Operating System :: OS Independent
Requires-Python: >=3.6
License-File: LICENSE
